my_own_package/__init__.py
eduard_1-0.1.0.dist-info/METADATA
eduard_1-0.1.0.dist-info/WHEEL
eduard_1-0.1.0.dist-info/top_level.txt
eduard_1-0.1.0.dist-info/RECORD
