Metadata-Version: 2.1
Name: eduard-1
Version: 0.1.0
Summary: primul package facut
Author: eduard
Author-email: vilaromservice@yahoo.com
License: UNKNOWN
Platform: UNKNOWN
